P2Ray/CLIApp.py
P2Ray/__init__.py
P2Ray/__main__.py
P2Ray/config_manager.py
P2Ray/config_parser.py
P2Ray/menu.py
P2Ray/protocol_test.py
P2Ray/settings.py
P2Ray/settings_menu.py
P2Ray/uri_encoder.py
P2Ray/utils.py
p2ray-0.0.2.1.dist-info/licenses/LICENSE
p2ray-0.0.2.1.dist-info/METADATA
p2ray-0.0.2.1.dist-info/WHEEL
p2ray-0.0.2.1.dist-info/entry_points.txt
p2ray-0.0.2.1.dist-info/top_level.txt
p2ray-0.0.2.1.dist-info/RECORD
