Metadata-Version: 2.4
Name: P2Ray
Version: 0.0.2.1
Summary: A V2ray vpn Client with a focus on config managment
Author-email: Parsa Roshanak <parsaroshanak@gmail.com>
License: LICENSE
Project-URL: Homepage, https://github.com/iparsw/P2Ray
Project-URL: Bug Tracker, https://github.com/yourname/iparsw/P2Ray
Requires-Python: >=3.10
License-File: LICENSE
Requires-Dist: emoji>=2.14.1
Requires-Dist: Pillow>=11.2.1
Requires-Dist: pyperclip>=1.9.0
Requires-Dist: qrcode>=8.2
Requires-Dist: Requests>=2.32.4
Requires-Dist: tabulate>=0.9.0
Requires-Dist: appdirs>=1.4.4
Dynamic: license-file
